ztooltip/__init__.py
ztooltip/constants.py
ztooltip/drop_shadow.py
ztooltip/enums.py
ztooltip/placement_utils.py
ztooltip/tooltip.py
ztooltip/tooltip_interface.py
ztooltip/tooltip_triangle.py
ztooltip/utils.py
ztooltip-2.0.0.dist-info/licenses/LICENSE
ztooltip-2.0.0.dist-info/METADATA
ztooltip-2.0.0.dist-info/WHEEL
ztooltip-2.0.0.dist-info/top_level.txt
ztooltip-2.0.0.dist-info/RECORD
