Metadata-Version: 2.4
Name: ZToolTip
Version: 2.0.0
Summary: A modern and fully customizable tooltip library for PyQt and PySide
Author: FaBuLuZz
License: MIT
Project-URL: Homepage, https://github.com/FaBuLuZz/ZToolTip
Keywords: python,qt,pyqt,pyside,tooltip,modern
Classifier: Programming Language :: Python :: 3
Classifier: Operating System :: OS Independent
Classifier: License :: OSI Approved :: MIT License
Requires-Python: >=3.7
License-File: LICENSE
Requires-Dist: pywin32>=311
Requires-Dist: QtPy>=2.4.1
Dynamic: license-file
